broom/__init__.py
broom/clusters.py
broom/compsep.py
broom/configurations.py
broom/gilcs.py
broom/gpilcs.py
broom/ilcs.py
broom/inputs.py
broom/leakage.py
broom/masking.py
broom/needlets.py
broom/pilcs.py
broom/routines.py
broom/saving.py
broom/seds.py
broom/simulations.py
broom/spectra.py
broom/templates.py
broom/configs/config_demo.yaml
broom/configs/config_groundbased.yaml
broom/configs/config_satellite.yaml
broom/utils/Cls_Planck2018_lensed_r0.fits
broom/utils/Cls_Planck2018_tensor_r1.fits
broom/utils/experiments.yaml
broom/utils/norm_nHits_SA_35FOV_ns512.fits
cmbroom-0.1.5.dist-info/licenses/LICENSE
cmbroom-0.1.5.dist-info/METADATA
cmbroom-0.1.5.dist-info/WHEEL
cmbroom-0.1.5.dist-info/top_level.txt
cmbroom-0.1.5.dist-info/RECORD
