Metadata-Version: 2.4
Name: cmbroom
Version: 0.1.5
Summary: A Python package for blind component separation of microwave sky maps.
Home-page: https://github.com/alecarones/broom
Author: Alessandro Carones
Author-email: Alessandro Carones <acarones@sissa.it>
License: GPL-3.0-or-later
Project-URL: Homepage, https://github.com/alecarones/broom
Project-URL: Source, https://github.com/alecarones/broom
Project-URL: Issues, https://github.com/alecarones/broom/issues
Requires-Python: >=3.10
License-File: LICENSE
Requires-Dist: astropy>=6.0.1
Requires-Dist: numpy>=1.18.5
Requires-Dist: scipy>=1.8
Requires-Dist: healpy>=1.15
Requires-Dist: pysm3>=3.3.2
Requires-Dist: mtneedlet>=0.0.5
Requires-Dist: threadpoolctl>=3.6.0
Provides-Extra: pymaster
Requires-Dist: pymaster>=2.4; extra == "pymaster"
Provides-Extra: docs
Requires-Dist: pdoc; extra == "docs"
Dynamic: author
Dynamic: home-page
Dynamic: license-file
Dynamic: requires-python
